graphmb/__init__.py
graphmb/amber_eval.py
graphmb/arg_options.py
graphmb/contigsdataset.py
graphmb/dgl_dataset.py
graphmb/evaluate.py
graphmb/gnn_models.py
graphmb/graphmb1.py
graphmb/graphsage_unsupervised.py
graphmb/layers.py
graphmb/main.py
graphmb/models.py
graphmb/train_ccvae.py
graphmb/train_gnn.py
graphmb/utils.py
graphmb/vamb_clustering.py
graphmb/version.py
graphmb/visualize.py
graphmb/data/Bacteria.ms
graphmb/data/kernel.npz
graphmb-0.2.5.dist-info/LICENSE
graphmb-0.2.5.dist-info/METADATA
graphmb-0.2.5.dist-info/WHEEL
graphmb-0.2.5.dist-info/entry_points.txt
graphmb-0.2.5.dist-info/top_level.txt
graphmb-0.2.5.dist-info/RECORD
