Metadata-Version: 2.1
Name: graphmb
Version: 0.2.5
Summary: UNKNOWN
Home-page: UNKNOWN
License: UNKNOWN
Platform: UNKNOWN
Requires-Python: >=3.8
License-File: LICENSE
Requires-Dist: importlib-resources
Requires-Dist: mlflow (==2.3.1)
Requires-Dist: networkx (==2.6.2)
Requires-Dist: requests
Requires-Dist: tensorflow (==2.11.1)
Requires-Dist: torch (==1.13.1)
Requires-Dist: tqdm (==4.61.2)
Requires-Dist: wheel
